mongoelastic/__init__.py
mongoelastic/mongoelastic.py
mongoelastic-0.0.9.dist-info/LICENSE
mongoelastic-0.0.9.dist-info/METADATA
mongoelastic-0.0.9.dist-info/WHEEL
mongoelastic-0.0.9.dist-info/top_level.txt
mongoelastic-0.0.9.dist-info/RECORD
