Metadata-Version: 2.1
Name: mongoelastic
Version: 0.0.9
Summary: MongoDB to Elasticsearch. Through this you can import data from mongoDB to elasticsearch.
Home-page: https://github.com/naimmalek/mongoelastic
Author: Naim Malek
Author-email: naim@peerbits.com
License: MIT
Download-URL: https://pypi.org/project/mongoelastic/
Keywords: mongodb,elasticsearch import,import mongodb to elasticsearch,elasticsearch,import mogno to es,import big data elasticsearch
Platform: UNKNOWN
Classifier: Programming Language :: Python :: 3
Classifier: License :: OSI Approved :: MIT License
Classifier: Operating System :: OS Independent
Requires-Python: >=3.5
Requires-Dist: elasticsearch (>=7.6.0)
Requires-Dist: progress (>=1.5)
Requires-Dist: pymongo (>=3.10.1)
